{
  "metaDescription": {
    "title": "Psicologo e Psicoterapeuta online",
    "description": "Psicologi e psicoterapeuti per ansia, depressione, disturbi psicologici, 7 giorni su 7, nessuna lista d'attesa."
  },
  "top-banner": {
    "title": "Psicologo e Psicoterapeuta online",
    "subtitle": "Se hai bisogno di parlare con qualcuno, nessun problema: con epiCura puoi parlare con i migliori psicologi e psicoterapeuti comodamente online, 7 giorni su 7, da smartphone, pc o tablet.<br><br><b>Il primo videoconsulto è gratuito</b>",
    "img": {
      "path": "psychology",
      "name": "psychology-header-new"
    },
    "has-large-title": true,
    "has-absolute-image": true,
    "first-image-order": false,
    "hide-image-mobile": false,
    "has-bg-color": "psychology",
    "cta-content": [
      {
        "label": "Inizia il tuo percorso",
        "link": "https://app.epicura.it/",
        "image": "",
        "variant": "gradient"
      }
    ]
  },
  "come_funziona": {
    "title": "Psicologo online, come funziona",
    "subtitle": "",
    "button": {
      "label": "Prenota videoconsulto gratuito",
      "link": "https://app.epicura.it/",
      "image": "",
      "variant": "gradient"
    },
    "cards": [
      {
        "image": {
          "path": "common",
          "name": "videoconsulto-white"
        },
        "title": "Prenota il videoconsulto gratuito",
        "text": "Nella fase di prenotazione, seleziona la data, l'orario e comunica le tue esigenze.",
        "has-background": true
      },
      {
        "image": {
          "path": "common",
          "name": "incontro-white"
        },
        "title": "Conosci <br /> il tuo psicologo",
        "text": "Abbiamo trovato il terapeuta adatto alle tue esigenze... è ora di conoscerlo!",
        "has-background": true
      },
      {
        "image": {
          "path": "common",
          "name": "psicologia-online-white"
        },
        "title": "Inizia <br /> la terapia",
        "text": "Terminato il primo videoconsulto gratuito, decidi se iniziare il tuo percorso psicologico.",
        "has-background": true
      }
    ]
  },
  "trattamenti": {
    "sectionTitle": "I nostri psicologi online si occupano di ",
    "altri_trattamenti": "Altri interventi di psicologia",
    "list": [
      {
        "link": "/ansia",
        "title": "Ansia",
        "description": "paure, fobie, attacchi di panico, disturbi psicosomatici, ipocondria, insonnia, ansia sociale"
      },
      {
        "link": "/sofferenza-psicologica",
        "title": "Sofferenza psicologica",
        "description": "stress, mobbing, burnout"
      },
      {
        "link": "/dipendenze",
        "title": "Dipendenze",
        "description": "affettiva, alcol, droga, gioco d’azzardo (ludopatia), social network, videogiochi, sesso"
      },
      {
        "link": "/depressione",
        "title": "Depressione",
        "description": "lutto, divorzio, fine relazione, patologie, malattie oncologiche, malattie croniche"
      },
      {
        "link": "/disturbo-della-personalita",
        "title": "Disturbo della personalità",
        "description": "ossessivo-compulsivo, borderline, narcisistico, paranoide, schizoide, schizotipico, antisociale, istrionico, evitante, dipendente"
      },
      {
        "link": "/disturbi-alimentari",
        "title": "Disturbi alimentari",
        "description": "anoressia, bulimia, fame compulsiva (binge-eating)"
      },
      {
        "link": "/terapia-di-coppia",
        "title": "Terapia di coppia",
        "description": "coppie in crisi, problemi di comunicazione, infedeltà, gelosia, divorzio, problemi sessuali, dipendenza affettiva, stati di frustrazione"
      },
      {
        "link": "/terapia-familiare",
        "title": "Terapia familiare",
        "description": "conflittualità familiari, disagi dell’età adolescenziale e pre-adolescenziale"
      }
    ]
  },
  "card-trattamenti": {
    "title": "In cosa possiamo aiutarti:",
    "cards": [
      {
        "url": "/ansia",
        "title": "Ansia",
        "description": "Paure, fobie, attacchi di panico, disturbi psicosomatici, ipocondria, insonnia, ansia sociale"
      },
      {
        "url": "/sofferenza-psicologica",
        "title": "Sofferenza psicologica",
        "description": "Stress, mobbing, burnout"
      },
      {
        "url": "/dipendenze",
        "title": "Dipendenze",
        "description": "Affettiva, alcol, droga, gioco d’azzardo (ludopatia), social network, videogiochi, sesso"
      },
      {
        "url": "/depressione",
        "title": "Depressione",
        "description": "Lutto, divorzio, fine relazione, patologie, malattie oncologiche, malattie croniche"
      },
      {
        "url": "/disturbo-della-personalita",
        "title": "Disturbo della personalità",
        "description": "Ossessivo-compulsivo, borderline, narcisistico, paranoide, schizoide, schizotipico, antisociale, istrionico, evitante, dipendente"
      },
      {
        "url": "/disturbi-alimentari",
        "title": "Disturbi alimentari",
        "description": "Anoressia, bulimia, fame compulsiva (binge-eating)"
      },
      {
        "url": "/terapia-di-coppia",
        "title": "Terapia di coppia",
        "description": "Coppie in crisi, problemi di comunicazione, infedeltà, gelosia, divorzio, problemi sessuali, dipendenza affettiva, stati di frustrazione"
      },
      {
        "url": "/terapia-familiare",
        "title": "Terapia familiare",
        "description": "Conflittualità familiari, disagi dell’età adolescenziale e pre-adolescenziale"
      }
    ]
  },
  "solutions": [
    {
      "title": "Terapia individuale e di coppia online",
      "subtitle": "Hai già effettuato il primo videoconsulto o vuoi continuare un percorso già iniziato?<br />Parla gratuitamente con un nostro tutor e scegli la soluzione più adatta alle tue esigenze.",
      "startingFromText": "",
      "solutionsBig": [
        {
          "title": "Terapia individuale",
          "text": "Inizia il tuo percorso con 2 o 4 videosedute mensili. Questa opzione è ideale se senti il bisogno di confrontarti con uno specialista per affrontare eventuali problematiche.",
          "startingFrom": false,
          "hideDiscount": true,
          "button": {
            "text": "Parla con un tutor",
            "link": "https://hubs.la/Q0150CxK0",
            "link-staging": "https://hubs.la/Q0150CxK0"
          },
          "priceCodes": [
            {
              "code": "psychologyIndividual2SessionsRemote",
              "label": "2 sedute "
            },
            {
              "code": "psychologyIndividual4SessionsRemote",
              "label": "4 sedute "
            }
          ]
        },
        {
          "title": "Terapia di coppia",
          "text": "Comincia questo percorso terapeutico di 2 o 4 videosedute mensili. Questo pacchetto è indicato quando uno o entrambi i partner si trovano in una situazione di disagio significativo e prolungato.",
          "startingFrom": false,
          "hideDiscount": true,
          "button": {
            "text": "Parla con un tutor",
            "link": "https://hubs.la/Q0150CxK0",
            "link-staging": "https://hubs.la/Q0150CxK0"
          },
          "priceCodes": [
            {
              "code": "psychologyCouples2SessionsRemote",
              "label": "2 sedute "
            },
            {
              "code": "psychologyCouples4SessionsRemote",
              "label": "4 sedute "
            }
          ]
        }
      ]
    }
  ],
  "advantages": {
    "title": "I migliori psicologi online entro 24 ore.",
    "subtitle": "Un servizio comodo, flessibile, affidabile",
    "list": [
      {
        "image": {
          "path": "common",
          "name": "specialist-2"
        },
        "title": "Solo professionisti <br /> qualificati",
        "description": "Verifichiamo nel dettaglio tutte le certificazioni acquisite e l’iscrizione all’Albo Ufficiale."
      },
      {
        "image": {
          "path": "common",
          "name": "certificate-2"
        },
        "title": "La tua soddisfazione <br /> è la nostra priorità",
        "description": "Se non dovessi trovarti bene con il professionista, ti garantiamo la sostituzione senza costi aggiuntivi."
      },
      {
        "image": {
          "path": "common",
          "name": "support-2"
        },
        "title": "Siamo sempre <br /> al tuo fianco",
        "description": "I nostri operatori sono attivi 7 giorni su 7 per offrirti un'assistenza su misura quando ne hai bisogno."
      }
    ]
  },
  "advantages-cards": {
    "title": "I vantaggi dello psicologo online epiCura",
    "cards": [
      {
        "title": "Dove vuoi",
        "text": "Accedi alla tua videoseduta dove e quando vuoi, da smartphone, pc o tablet. Il nostro servizio è strutturato a completa garanzia della tua privacy.",
        "img": {
          "path": "psychology",
          "name": "smartphone"
        }
      },
      {
        "title": "Evita gli spostamenti",
        "text": "epiCura ti permette di accedere alle videosedute in modo semplice e rapido, ovunque tu sia, senza necessità di recarti nello studio del professionista.",
        "img": {
          "path": "psychology",
          "name": "evita-spostamenti"
        }
      },
      {
        "title": "Paga online",
        "text": "Con epiCura puoi prenotare e pagare comodamente da sito, in pochi clic e in totale sicurezza, con carta di credito, bancomat oppure prepagata.",
        "img": {
          "path": "psychology",
          "name": "pagamento-online"
        }
      }
    ]
  },
  "top-psycho-cards": {
    "title": "I migliori psicologi e psicoterapeuti online",
    "subtitle": "Un servizio comodo, flessibile, affidabile",
    "cards": [
      {
        "title": "Solo professionisti <br /> qualificati",
        "text": "Verifichiamo nel dettaglio tutte le certificazioni acquisite e l’iscrizione all’Albo Ufficiale.",
        "img": {
          "path": "common",
          "name": "convenient"
        }
      },
      {
        "title": "La tua soddisfazione <br /> è la nostra priorità",
        "text": "Se non dovessi trovarti bene con il professionista, ti garantiamo la sostituzione senza costi aggiuntivi.",
        "img": {
          "path": "common",
          "name": "pro-certified"
        }
      },
      {
        "title": "Siamo sempre <br /> al tuo fianco",
        "text": "I nostri operatori sono attivi 7 giorni su 7 per offrirti un'assistenza su misura quando ne hai bisogno.",
        "img": {
          "path": "common",
          "name": "support"
        }
      }
    ]
  },
  "service-banner": {
    "title": "Hai un dubbio sul servizio di psicologia? Chiamaci",
    "subtitle": "Il nostro team sarà felice di fornirti tutte le informazioni necessarie per prenotare i servizi epiCura più adatti alle tue esigenze.",
    "img": {
      "path": "psychology",
      "name": "psychology-service-banner"
    },
    "has-large-title": false,
    "has-absolute-image": true,
    "first-image-order": false,
    "hide-image-mobile": false,
    "has-bg-color": "psychology",
    "cta-content": [
      {
        "label": "800 909 209",
        "link": "tel:800909209",
        "img": {},
        "variant": "gradient"
      }
    ]
  },
  "service-cards": {
    "title": "Puoi prenotare anche",
    "cards": [
      {
        "title": "Visite mediche, esami strumentali e videoconsulti",
        "subtitle": "online - a domicilio - in studio",
        "img": "/img/visite-mediche-gradient.png",
        "img-hover": "/img/visite-mediche-white.png",
        "cta-label": "Prenota",
        "url": "/servizi/"
      },
      {
        "title": "Ricerca e selezione badanti, assistenza domiciliare ad ore",
        "subtitle": "a domicilio",
        "img": "/img/ricerca-badante-gradient.png",
        "img-hover": "/img/ricerca-badante-white.png",
        "cta-label": "Prenota",
        "url": "/badante/"
      }
    ]
  }
}
